shopee/__init__.py
shopee/base.py
shopee/category.py
shopee/client.py
shopee/item.py
shopee/logistic.py
shopee/order.py
shopee/product.py
shopee/rma.py
shopee/setting.py
shopee/variation.py
shopee_api-1.0.3.dist-info/METADATA
shopee_api-1.0.3.dist-info/WHEEL
shopee_api-1.0.3.dist-info/top_level.txt
shopee_api-1.0.3.dist-info/RECORD
