Metadata-Version: 2.1
Name: shopee-api
Version: 1.0.3
Summary: simple python shopee partner api client
Home-page: https://github.com/ketu/shopee_api
Author: ketu.lai
Author-email: ketu.lai@gmail.com
License: MIT
Keywords: shopee api
Platform: UNKNOWN
Requires-Python: >=3.6
